rnginline/__init__.py
rnginline/cmdline.py
rnginline/constants.py
rnginline/exceptions.py
rnginline/postprocess.py
rnginline/py.typed
rnginline/regexbuilder.py
rnginline/relaxng.rng
rnginline/test/__init__.py
rnginline/test/data/datatype-library-inheritance/base-external.rng
rnginline/test/data/datatype-library-inheritance/base-included.rng
rnginline/test/data/datatype-library-inheritance/external.rng
rnginline/test/data/datatype-library-inheritance/included.rng
rnginline/test/data/datatype-library-propagation/a.rng
rnginline/test/data/datatype-library-propagation/b.rng
rnginline/test/data/include-invalid-xml/invalid-xml.rng
rnginline/test/data/include-invalid-xml/ok.rng
rnginline/test/data/include-non-rng-xml/invalid-xml.rng
rnginline/test/data/include-non-rng-xml/ok.rng
rnginline/test/data/include-override-define/included.rng
rnginline/test/data/include-override-define/start.rng
rnginline/test/data/include-override-start/included.rng
rnginline/test/data/include-override-start/start.rng
rnginline/test/data/inline-non-grammar-els/foo-el.rng
rnginline/test/data/inline-non-grammar-els/grammar-foo-el.rng
rnginline/test/data/inline-non-grammar-els/illegal.rng
rnginline/test/data/inline-non-grammar-els/legal.rng
rnginline/test/data/loops/foo/a.rng
rnginline/test/data/loops/foo/bar/baz/b.rng
rnginline/test/data/loops/start.rng
rnginline/test/data/multiple-ref-1-fetch/a/b/c/popular.rng
rnginline/test/data/multiple-ref-1-fetch/indirect.rng
rnginline/test/data/multiple-ref-1-fetch/schema.rng
rnginline/test/data/testcases/datatype-library-external/external.rng
rnginline/test/data/testcases/datatype-library-external/included.rng
rnginline/test/data/testcases/datatype-library-external/positive.xml
rnginline/test/data/testcases/datatype-library-external/schema.rng
rnginline/test/data/testcases/external-ref-1/README.rst
rnginline/test/data/testcases/external-ref-1/baz.rnc
rnginline/test/data/testcases/external-ref-1/baz.rng
rnginline-1.0.0.dist-info/LICENSE.txt
rnginline-1.0.0.dist-info/METADATA
rnginline-1.0.0.dist-info/WHEEL
rnginline-1.0.0.dist-info/entry_points.txt
rnginline-1.0.0.dist-info/RECORD
