Metadata-Version: 2.1
Name: rnginline
Version: 1.0.0
Summary: Flatten multi-file RELAX NG schemas
Home-page: https://github.com/h4l/rnginline
License: Apache-2.0
Keywords: relaxng,inline,lxml,xml
Author: Hal Blackburn
Author-email: hwtb2@cam.ac.uk
Requires-Python: >=3.7,<4.0
Classifier: Environment :: Console
Classifier: Intended Audience :: Developers
Classifier: Intended Audience :: End Users/Desktop
Classifier: License :: OSI Approved :: Apache Software License
Classifier: Programming Language :: Python :: 3
Classifier: Programming Language :: Python :: 3.7
Classifier: Programming Language :: Python :: 3.8
Classifier: Programming Language :: Python :: 3.9
Classifier: Programming Language :: Python :: 3.10
Classifier: Programming Language :: Python :: 3.11
Classifier: Programming Language :: Python :: 3
Classifier: Programming Language :: Python :: 3.11
Classifier: Programming Language :: Python :: 3.7
Classifier: Topic :: Software Development :: Build Tools
Classifier: Topic :: Software Development :: Libraries :: Python Modules
Classifier: Topic :: Text Processing :: Markup :: XML
Requires-Dist: docopt-ng (>=0.8.1,<0.9.0)
Requires-Dist: importlib-metadata (>=6.6.0,<7.0.0)
Requires-Dist: lxml (>=4,<5)
Requires-Dist: typing-extensions (>=4.5.0,<5.0.0)
Project-URL: Documentation, https://rnginline.readthedocs.io/en/latest/
Project-URL: Repository, https://github.com/h4l/rnginline
